kapwrapper/__init__.py
kapwrapper/models.py
kapwrapper/wrapper.py
kap_wrapper-0.2.5.dist-info/LICENSE
kap_wrapper-0.2.5.dist-info/METADATA
kap_wrapper-0.2.5.dist-info/WHEEL
kap_wrapper-0.2.5.dist-info/top_level.txt
kap_wrapper-0.2.5.dist-info/RECORD
