Metadata-Version: 2.1
Name: kap-wrapper
Version: 0.2.5
Summary: Kap wrapper to fetch funds data from http://kap.org.tr/
Home-page: https://github.com/semudu/kap-wrapper
Download-URL: https://github.com/semudu/kap-wrapper/archive/v0.2.5.tar.gz
Author: Serhat Durmaz
Author-email: serhat.md@gmail.com
License: MIT
Keywords: KAP,WRAPPER,FUND,FON
Classifier: Development Status :: 5 - Production/Stable
Classifier: Intended Audience :: Developers
Classifier: Topic :: Software Development :: Build Tools
Classifier: License :: OSI Approved :: MIT License
Classifier: Programming Language :: Python :: 3
Classifier: Operating System :: OS Independent
Requires-Python: >=3.8
License-File: LICENSE
Requires-Dist: requests
Requires-Dist: lxml
